{
  "ui_button_archive": "Open Archive",
  "ui_button_build": "Construct",
  "ui_button_copy_code": "Copy Code",
  "ui_button_dismiss": "Acknowledged",
  "ui_button_ending": "Begin Transmission",
  "ui_button_install": "Install",
  "ui_button_letters": "Read Messages",
  "ui_button_provision": "Provision",
  "ui_button_reconnect": "Reconnect",
  "ui_button_redeem_code": "Redeem Code",
  "ui_button_save_wifi": "Save Uplink",
  "ui_button_settings": "System Config",
  "ui_button_sync": "Sync",
  "ui_button_tend": "Tend",
  "ui_button_trade": "Barter",
  "ui_header_actions": "Operations",
  "ui_header_archive": "Recovered Archive",
  "ui_header_away": "While You Were Away",
  "ui_header_ending": "Final Transmission",
  "ui_header_events": "System Log",
  "ui_header_firmware": "Firmware",
  "ui_header_hab_status": "Hab Status",
  "ui_header_letters": "Crew Messages",
  "ui_header_modules": "Modules",
  "ui_header_population": "Colony Roster",
  "ui_header_resources": "Resources",
  "ui_header_wifi": "Uplink",
  "ui_resource_alloy": "Alloy",
  "ui_resource_atmosphere": "Atmosphere",
  "ui_resource_biomass": "Biomass",
  "ui_resource_food": "Rations",
  "ui_resource_ice": "Ice",
  "ui_resource_o2": "O₂",
  "ui_resource_polymer": "Polymer",
  "ui_resource_population": "Crew",
  "ui_resource_power": "Power",
  "ui_resource_rare_metals": "Rare Metals",
  "ui_resource_regolith": "Regolith",
  "ui_resource_temperature": "Surface Temp",
  "ui_resource_water": "Water",
  "ui_tab_archive": "Archive",
  "ui_tab_colony": "Colony",
  "ui_tab_ending": "Transmission",
  "ui_tab_hab": "Hab",
  "ui_tab_surface": "Surface",
  "ui_tab_terraform": "Terraform",
  "ui_tab_trade": "Trade",
  "ui_tip_act_gate": "The colony must grow first.",
  "ui_tip_archive_unlock": "New archive entry recovered.",
  "ui_tip_catchup": "Catch-up in progress.",
  "ui_tip_content_stub": "Signal too faint. Keep listening.",
  "ui_tip_cooldown": "Systems cycling. Stand by.",
  "ui_tip_ending_locked": "The story is not yet finished.",
  "ui_tip_gateway": "Requires gateway connection.",
  "ui_tip_insufficient": "Insufficient resources.",
  "ui_tip_locked": "Not yet available.",
  "ui_tip_no_repeat": "Already completed.",
  "ui_tip_offline": "Uplink offline.",
  "ui_tip_passport": "Colony passport required.",
  "ui_tip_power_cycle": "Power cycle recommended.",
  "ui_tip_protected_save": "Progress saved to local storage."
}